data_mem.v
module data_mem (
    input clk,
    input mem_read,
    input mem_write,
    input [31:0] addr,
    input [31:0] write_data,
    output reg [31:0] read_data
);

    reg [31:0] memory [0:1023]; // 1K words = 4KB memory

    wire [9:0] word_addr = addr[11:2]; // word-aligned

    always @(posedge clk) begin
        if (mem_write) begin
            memory[word_addr] <= write_data;
        end
    end

    always @(*) begin
        if (mem_read)
            read_data = memory[word_addr];
        else
            read_data = 32'd0;
    end

endmodule

alu.v
module alu (
    input [31:0] a, b,
    input [4:0] shamt,              // shift amount for shift ops
    input [3:0] alu_control,        // control signal selects operation
    output reg [31:0] result,
    output zero
);

    wire signed [31:0] a_signed = a;
    wire signed [31:0] b_signed = b;

    always @(*) begin
        case (alu_control)
            4'b0000: result = a & b;                    // and
            4'b0001: result = a | b;                    // or
            4'b0010: result = a + b;                    // add
            4'b0011: result = a - b;                    // sub
            4'b0100: result = a ^ b;                    // xor
            4'b0101: result = ~a;                       // not
            4'b0110: result = a << shamt;               // sll
            4'b0111: result = a >> shamt;               // srl
            4'b1000: result = a_signed >>> shamt;       // sra
            4'b1001: result = (a_signed < b_signed) ? 32'd1 : 32'd0; // slt
            4'b1010: result = (a == b) ? 32'd1 : 32'd0;  // seq
            default: result = 32'd0;
        endcase
    end

    assign zero = (result == 0);

endmodule

register_file.v
module register_file (
    input clk,
    input reset,
    input reg_write,
    input [4:0] rs, rt, rd,       // Source and destination register indices
    input [31:0] write_data,      // Data to write into rd
    output [31:0] read_data1,     // Output of rs
    output [31:0] read_data2      // Output of rt
);

    reg [31:0] registers [0:31];  // 32 general-purpose registers
    (* keep *) reg [31:0] register [0:31];  // Makes it visible in waveform + hierarchical references


    integer i;

    // Reset all registers to 0
    always @(posedge reset) begin
        for (i = 0; i < 32; i = i + 1)
            registers[i] <= 32'd0;
    end

    // Write on rising clock edge
    always @(posedge clk) begin
        if (reg_write && rd != 0)  // Register 0 is hardwired to zero
            registers[rd] <= write_data;
    end

    // Asynchronous read
    assign read_data1 = (rs != 0) ? registers[rs] : 32'd0;
    assign read_data2 = (rt != 0) ? registers[rt] : 32'd0;

endmodule

controller.v
module controller (
    input [5:0] opcode,
    input [5:0] funct,
    output reg reg_dst,
    output reg alu_src,
    output reg mem_to_reg,
    output reg reg_write,
    output reg mem_read,
    output reg mem_write,
    output reg branch,
    output reg jump,
    output reg [3:0] alu_control
);

    always @(*) begin
        // Default values
        reg_dst     = 0;
        alu_src     = 0;
        mem_to_reg  = 0;
        reg_write   = 0;
        mem_read    = 0;
        mem_write   = 0;
        branch      = 0;
        jump        = 0;
        alu_control = 4'b0000;

        case (opcode)
            6'b000000: begin  // R-type
                reg_dst    = 1;
                reg_write  = 1;
                alu_src    = 0;
                case (funct)
                    6'b100000: alu_control = 4'b0010; // add
                    6'b100010: alu_control = 4'b0011; // sub
                    6'b100100: alu_control = 4'b0000; // and
                    6'b100101: alu_control = 4'b0001; // or
                    6'b100110: alu_control = 4'b0100; // xor
                    6'b100111: alu_control = 4'b0101; // not
                    6'b000000: alu_control = 4'b0110; // sll
                    6'b000010: alu_control = 4'b0111; // srl
                    6'b000011: alu_control = 4'b1000; // sra
                    6'b101010: alu_control = 4'b1001; // slt
                    6'b101001: alu_control = 4'b1010; // seq
                    default:   alu_control = 4'b0000;
                endcase
            end

            6'b001000: begin // addi
                reg_dst     = 0;
                reg_write   = 1;
                alu_src     = 1;
                alu_control = 4'b0010;
            end

            6'b100011: begin // lw
                reg_dst     = 0;
                alu_src     = 1;
                mem_to_reg  = 1;
                reg_write   = 1;
                mem_read    = 1;
                alu_control = 4'b0010;
            end

            6'b101011: begin // sw
                alu_src     = 1;
                mem_write   = 1;
                alu_control = 4'b0010;
            end

            6'b000100: begin // beq
                branch      = 1;
                alu_control = 4'b0011;
            end

            6'b000010: begin // j
                jump = 1;
            end

            default: begin
                // Keep all control signals default
            end
        endcase
    end

endmodule

decoder.v
module decoder(
    input [31:0] instruction,
    output [5:0] opcode,
    output [4:0] rs, rt, rd,
    output [4:0] shamt,
    output [5:0] funct,
    output [15:0] immediate,
    output [25:0] address
);

assign opcode    = instruction[31:26];
assign rs        = instruction[25:21];
assign rt        = instruction[20:16];
assign rd        = instruction[15:11];
assign shamt     = instruction[10:6];
assign funct     = instruction[5:0];
assign immediate = instruction[15:0];
assign address   = instruction[25:0];

endmodule

instruction_mem.v
module instruction_mem (
    input [31:0] addr,
    output [31:0] instruction
);
    reg [31:0] memory [0:255]; // 1 KB instr mem
//    memory[31] = 

    initial begin
//         memory[0] = 32'b00100000000010000000000000001010; // addi $8, $0, 10
//         memory[1] = 32'b00100000000010010000000000000110; // addi $9, $0, 6
//         memory[2] = 32'b00010101000010010000000000000010; // bleq  $8, $9, label (offset = 2) 
//         memory[3] = 32'b00100000000010100000000011111111; // addi $10, $0, 255 (skipped if branch taken)
//         memory[4] = 32'b00100000000010110000000000001010; // addi $11, $0, 10
//         memory[5] = 32'b00000001000010010110000000011000; // mul-low $12, $8, $9
         //memory[6] = 32'b00000001000010            // mul-high $13 ,$8,$9
         
//         memory[0] = 32'b00100000000010000000000000000101; // addi $8, $0, 5
//         memory[1] = 32'b00100000000010010000000000001010; // addi $9, $0, 10
//         memory[2] = 32'b00000001000010010101000000100000; // add  $10,$8,$9
//         memory[3] = 32'b10101101000010100000000000000000; // sw   $10, 0($8)
//         memory[4] = 32'b10001101000010110000000000000000; // lw   $11, 0($8)

         // addi $8, $0, 20000
//        memory[0] = 32'b001000_00000_01000_0000000110010000; // 0x20084E20

//        // addi $9, $0, 30000
//        memory[1] = 32'b001000_00000_01001_0000000111010011; // 0x20097310

//        // mult $8, $9
//        memory[2] = 32'b000000_01000_01001_00000_00000_011000; // funct = 24 (0x18)

        // mflo $10
        //memory[3] = 32'b000000_00000_00000_01010_00000_010010; // funct = 18 (0x12)

        // mfhi $11
        //memory[4] = 32'b000000_00000_00000_01011_00000_010000; // funct = 16 (0x10)

        //insertion sort
           
         memory[0] = 32'b00100000000111110000000000000111;  //storing number of values=7 for insertion sort in $31
         memory[1] = 32'b00100000000000010000000000000000; // addi $1, $0, 0
         memory[2] = 32'b00100000001000010000000000000001; // addi $1, $1, 1
         memory[3] = 32'b00010000001111110000000001100100; // beq  $1, $31, 100
         memory[4] = 32'b00100000001000101111111111111111; // addi $2, $1, -1
         memory[5] = 32'b00100000010001010000000000000001; // add  $5, $2, 1
         memory[6] = 32'b10001100010001110000000000000000; // lw   $7, 0($2)
         memory[7] = 32'b10001100101010000000000000000000; // lw   $8, 0($5)
         memory[8] = 32'b00010100111010001111111111111001; // bleq $7, $8, -7 
         memory[9] = 32'b10101100101001110000000000000000; // sw   $7, 0($5)
         memory[10] = 32'b10101100010010000000000000000000; // sw   $8, 0($2)
         memory[11] = 32'b00010000010000001111111111110110; // beq  $2, $0, -10
         memory[12] = 32'b00100000010000101111111111111111; // addi $2, $2, -1
         memory[13] = 32'b00010000000000001111111111110111; // beq  $0, $0, -9
    end

    assign instruction = memory[addr[31:2]]; // word-aligned
endmodule

pc.v
module pc(
    input clk,
    input reset,
    input [31:0] next_pc,
    output reg [31:0] curr_pc
);

always @(posedge clk or posedge reset) begin
    if (reset)
        curr_pc <= 32'h00000000;
    else
        curr_pc <= next_pc;
end

endmodule

top.v
`timescale 1ns / 1ps

module top (
    input clk,
    input reset
);

    // Program Counter and Instruction
    wire [31:0] pc_current;
    wire [31:0] pc_next;
    wire [31:0] instruction;

    // Instruction Fields
    wire [5:0] opcode, funct;
    wire [4:0] rs, rt, rd, shamt;
    wire [15:0] immediate;
    wire [25:0] address;

    // Register outputs
    wire [31:0] reg_data1, reg_data2, write_data;
    wire [31:0] alu_input_b;
    wire [31:0] alu_result;
    wire zero;

    // Control Signals
    wire reg_dst, alu_src, mem_to_reg, reg_write;
    wire mem_read, mem_write, branch, jump;
    
    wire [3:0] alu_control;
    wire [4:0] write_reg;

    // === PC Logic ===
    pc pc_inst (
        .clk(clk),
        .reset(reset),
        .next_pc(pc_next),
        .curr_pc(pc_current)
    );

    assign pc_next = pc_current + 4; // no branching yet

    // === Instruction Memory ===
    instruction_mem imem (
        .addr(pc_current),
        .instruction(instruction)
    );

    // === Decoder ===
    decoder decode (
        .instruction(instruction),
        .opcode(opcode),
        .rs(rs),
        .rt(rt),
        .rd(rd),
        .shamt(shamt),
        .funct(funct),
        .immediate(immediate),
        .address(address)
    );

    // === Controller ===
    controller control_unit (
        .opcode(opcode),
        .funct(funct),
        .reg_dst(reg_dst),
        .alu_src(alu_src),
        .mem_to_reg(mem_to_reg),
        .reg_write(reg_write),
        .mem_read(mem_read),
        .mem_write(mem_write),
        .branch(branch),
        .jump(jump),
        .alu_control(alu_control)
    );

    // === Register File ===
    assign write_reg = (reg_dst) ? rd : rt;

    register_file reg_file (
        .clk(clk),
        .reset(reset),
        .reg_write(reg_write),
        .rs(rs),
        .rt(rt),
        .rd(write_reg),
        .write_data(write_data),
        .read_data1(reg_data1),
        .read_data2(reg_data2)
    );

    // === ALU Operand Select ===
    assign alu_input_b = (alu_src) ? {{16{immediate[15]}}, immediate} : reg_data2;

    alu alu_inst (
        .a(reg_data1),
        .b(alu_input_b),
        .shamt(shamt),
        .alu_control(alu_control),
        .result(alu_result),
        .zero(zero)
    );

    // === Data Memory Placeholder ===
    assign write_data = alu_result; // for now (no mem_to_reg support yet)

    // === Data Memory ===
    wire [31:0] mem_data_out;

    data_mem dmem (
        .clk(clk),
        .mem_read(mem_read),
        .mem_write(mem_write),
        .addr(alu_result),
        .write_data(reg_data2),
        .read_data(mem_data_out)
    );

    // === Write-back mux ===
    assign write_data = (mem_to_reg) ? mem_data_out : alu_result;

    always @(posedge clk) begin
    $display("PC: %h | Instruction: %h", pc_current, instruction);
    end


    always @(posedge clk) begin
    if (!reset) begin
        $display("reg[8] (t0)  = %d", reg_file.register[8]);
        $display("reg[9] (t1)  = %d", reg_file.register[9]);
        $display("reg[10] (t2) = %d", reg_file.register[10]);
        $display("reg[11] (t3) = %d", reg_file.register[11]);
        $display("mem[0]       = %d", dmem.memory[0]);
    end
    end


endmodule

testbench.v
`timescale 1ns / 1ps

module testbench;

    reg clk = 0;
    reg reset = 1;

    // Clock generator
    always #5 clk = ~clk;

    // Instantiate the top module
    top dut (
        .clk(clk),
        .reset(reset)
    );

    initial begin
        $monitor("Time: %0t | PC: %h | Instruction: %h | Reg[8]: %h | Reg[9]: %h | Reg[10]: %h", 
                         $time, dut.pc_current, dut.instruction, dut.reg_file.registers[8], 
                         dut.reg_file.registers[9], dut.reg_file.registers[10]);
        $display("===== IITK-Mini-MIPS Simulation Start =====");
        $dumpfile("cpu.vcd");
        $dumpvars(0, dut);

        #10 reset = 0;

        #100 $display("===== Simulation Done =====");
        $finish;
    end

endmodule

cpu.vcd
$date
	Thu Apr 17 16:20:48 2025
$end
$version
	Icarus Verilog
$end
$timescale
	1ps
$end
$scope module testbench $end
$scope module dut $end
$var wire 26 ! address [25:0] $end
$var wire 4 " alu_control [3:0] $end
$var wire 32 # alu_input_b [31:0] $end
$var wire 32 $ alu_result [31:0] $end
$var wire 1 % alu_src $end
$var wire 1 & branch $end
$var wire 1 ' clk $end
$var wire 6 ( funct [5:0] $end
$var wire 16 ) immediate [15:0] $end
$var wire 32 * instruction [31:0] $end
$var wire 1 + jump $end
$var wire 32 , mem_data_out [31:0] $end
$var wire 1 - mem_read $end
$var wire 1 . mem_to_reg $end
$var wire 1 / mem_write $end
$var wire 6 0 opcode [5:0] $end
$var wire 32 1 pc_current [31:0] $end
$var wire 32 2 pc_next [31:0] $end
$var wire 5 3 rd [4:0] $end
$var wire 32 4 reg_data1 [31:0] $end
$var wire 32 5 reg_data2 [31:0] $end
$var wire 1 6 reg_dst $end
$var wire 1 7 reg_write $end
$var wire 1 8 reset $end
$var wire 5 9 rs [4:0] $end
$var wire 5 : rt [4:0] $end
$var wire 5 ; shamt [4:0] $end
$var wire 32 < write_data [31:0] $end
$var wire 5 = write_reg [4:0] $end
$var wire 1 > zero $end
$scope module pc_inst $end
$var wire 1 ' clk $end
$var wire 32 ? next_pc [31:0] $end
$var wire 1 8 reset $end
$var reg 32 @ curr_pc [31:0] $end
$upscope $end
$scope module imem $end
$var wire 32 A addr [31:0] $end
$var wire 32 B instruction [31:0] $end
$upscope $end
$scope module decode $end
$var wire 26 C address [25:0] $end
$var wire 6 D funct [5:0] $end
$var wire 16 E immediate [15:0] $end
$var wire 32 F instruction [31:0] $end
$var wire 6 G opcode [5:0] $end
$var wire 5 H rd [4:0] $end
$var wire 5 I rs [4:0] $end
$var wire 5 J rt [4:0] $end
$var wire 5 K shamt [4:0] $end
$upscope $end
$scope module control_unit $end
$var wire 6 L funct [5:0] $end
$var wire 6 M opcode [5:0] $end
$var reg 4 N alu_control [3:0] $end
$var reg 1 O alu_src $end
$var reg 1 P branch $end
$var reg 1 Q jump $end
$var reg 1 R mem_read $end
$var reg 1 S mem_to_reg $end
$var reg 1 T mem_write $end
$var reg 1 U reg_dst $end
$var reg 1 V reg_write $end
$upscope $end
$scope module reg_file $end
$var wire 1 ' clk $end
$var wire 5 W rd [4:0] $end
$var wire 32 X read_data1 [31:0] $end
$var wire 32 Y read_data2 [31:0] $end
$var wire 1 7 reg_write $end
$var wire 1 8 reset $end
$var wire 5 Z rs [4:0] $end
$var wire 5 [ rt [4:0] $end
$var wire 32 \ write_data [31:0] $end
$var integer 32 ] i [31:0] $end
$upscope $end
$scope module alu_inst $end
$var wire 32 ^ a [31:0] $end
$var wire 32 _ a_signed [31:0] $end
$var wire 4 ` alu_control [3:0] $end
$var wire 32 a b [31:0] $end
$var wire 32 b b_signed [31:0] $end
$var wire 5 c shamt [4:0] $end
$var wire 1 > zero $end
$var reg 32 d result [31:0] $end
$upscope $end
$scope module dmem $end
$var wire 32 e addr [31:0] $end
$var wire 1 ' clk $end
$var wire 1 - mem_read $end
$var wire 1 / mem_write $end
$var wire 10 f word_addr [9:0] $end
$var wire 32 g write_data [31:0] $end
$var reg 32 h read_data [31:0] $end
$upscope $end
$upscope $end
$upscope $end
$enddefinitions $end
#0
$dumpvars
b0 h
b0 g
b1 f
b101 e
b101 d
b0 c
b101 b
b101 a
b10 `
b0 _
b0 ^
b100000 ]
b101 \
b1000 [
b0 Z
b0 Y
b0 X
b1000 W
1V
0U
0T
0S
0R
0Q
0P
1O
b10 N
b1000 M
b101 L
b0 K
b1000 J
b0 I
b0 H
b1000 G
b100000000010000000000000000101 F
b101 E
b101 D
b10000000000000000101 C
b100000000010000000000000000101 B
b0 A
b0 @
b100 ?
0>
b1000 =
b101 <
b0 ;
b1000 :
b0 9
18
17
06
b0 5
b0 4
b0 3
b100 2
b0 1
b1000 0
0/
0.
0-
b0 ,
0+
b100000000010000000000000000101 *
b101 )
b101 (
0'
0&
1%
b101 $
b101 #
b10 "
b10000000000000000101 !
$end
#5000
b101 5
b101 Y
b101 g
1'
#10000
0'
08
#15000
b10 f
b1010 d
b1010 $
b1010 e
b1010 <
b1010 \
b0 5
b0 Y
b0 g
b1001 =
b1001 W
b10 N
b10 "
b10 `
1V
17
1O
1%
b1010 b
b1010 #
b1010 a
b1001 :
b1001 J
b1001 [
b1010 (
b1010 D
b1010 L
b1010 )
b1010 E
b10010000000000001010 !
b10010000000000001010 C
b100000000010010000000000001010 *
b100000000010010000000000001010 B
b100000000010010000000000001010 F
b1000 2
b1000 ?
b100 @
b100 1
b100 A
1'
#20000
0'
#25000
b11 f
b1010 =
b1010 W
b1111 d
b1111 $
b1111 e
b1111 <
b1111 \
b101 _
b101 4
b101 X
b101 ^
1U
16
b10 N
b10 "
b10 `
1V
17
0O
0%
b1010 b
b1010 #
b1010 a
b0 0
b0 G
b0 M
b1000 9
b1000 I
b1000 Z
b1010 3
b1010 H
b100000 (
b100000 D
b100000 L
b101000000100000 )
b101000000100000 E
b1000010010101000000100000 !
b1000010010101000000100000 C
b1010 5
b1010 Y
b1010 g
b1000010010101000000100000 *
b1000010010101000000100000 B
b1000010010101000000100000 F
b1100 2
b1100 ?
b1000 @
b1000 1
b1000 A
1'
#30000
0'
#35000
1>
b0 f
b0 b
b0 #
b0 a
b0 d
b0 $
b0 e
b0 <
b0 \
b0 _
b0 4
b0 X
b0 ^
b1111 5
b1111 Y
b1111 g
1T
1/
1O
1%
b10 N
b10 "
b10 `
0V
07
0U
06
b101011 0
b101011 G
b101011 M
b0 9
b0 I
b0 Z
b1010 :
b1010 J
b1010 [
b0 3
b0 H
b0 (
b0 D
b0 L
b0 )
b0 E
b10100000000000000000 !
b10100000000000000000 C
b10101100000010100000000000000000 *
b10101100000010100000000000000000 B
b10101100000010100000000000000000 F
b10000 2
b10000 ?
b1100 @
b1100 1
b1100 A
1'
#40000
0'
#45000
b0xxxx <
b0xxxx \
b1111 h
b1111 ,
1R
1-
1V
17
1S
1.
b10 N
b10 "
b10 `
0T
0/
1O
1%
b0 5
b0 Y
b0 g
b1011 =
b1011 W
b100011 0
b100011 G
b100011 M
b1011 :
b1011 J
b1011 [
b10110000000000000000 !
b10110000000000000000 C
b10001100000010110000000000000000 *
b10001100000010110000000000000000 B
b10001100000010110000000000000000 F
b10100 2
b10100 ?
b10000 @
b10000 1
b10000 A
1'
#50000
0'
#55000
bx f
bx d
x>
bx $
bx e
b0 h
b0 ,
bx <
bx \
bx _
bx 4
bx X
bx ^
bx =
bx W
b0 N
b0 "
b0 `
0R
0-
0V
07
0S
0.
0O
0%
bx b
bx #
bx a
bx 0
bx G
bx M
bx 9
bx I
bx Z
bx :
bx J
bx [
bx 3
bx H
bx ;
bx K
bx c
bx (
bx D
bx L
bx )
bx E
bx !
bx C
bx 5
bx Y
bx g
bx *
bx B
bx F
b11000 2
b11000 ?
b10100 @
b10100 1
b10100 A
1'
#60000
0'
#65000
b11100 2
b11100 ?
b11000 @
b11000 1
b11000 A
1'
#70000
0'
#75000
b100000 2
b100000 ?
b11100 @
b11100 1
b11100 A
1'
#80000
0'
#85000
b100100 2
b100100 ?
b100000 @
b100000 1
b100000 A
1'
#90000
0'
#95000
b101000 2
b101000 ?
b100100 @
b100100 1
b100100 A
1'
#100000
0'
#105000
b101100 2
b101100 ?
b101000 @
b101000 1
b101000 A
1'
#110000
0'
#115000
b110000 2
b110000 ?
b101100 @
b101100 1
b101100 A
1'
#120000
0'
#125000
b110100 2
b110100 ?
b110000 @
b110000 1
b110000 A
1'
#130000
0'
#135000
b111000 2
b111000 ?
b110100 @
b110100 1
b110100 A
1'
#140000
0'
#145000
b111100 2
b111100 ?
b111000 @
b111000 1
b111000 A
1'
#150000
0'
#155000
b1000000 2
b1000000 ?
b111100 @
b111100 1
b111100 A
1'
#160000
0'
#165000
b1000100 2
b1000100 ?
b1000000 @
b1000000 1
b1000000 A
1'
#170000
0'
#175000
b1001000 2
b1001000 ?
b1000100 @
b1000100 1
b1000100 A
1'
#180000
0'
#185000
b1001100 2
b1001100 ?
b1001000 @
b1001000 1
b1001000 A
1'
#190000
0'
#195000
b1010000 2
b1010000 ?
b1001100 @
b1001100 1
b1001100 A
1'
#200000
0'
#205000
b1010100 2
b1010100 ?
b1010000 @
b1010000 1
b1010000 A
1'
#210000
0'
#215000
b1011000 2
b1011000 ?
b1010100 @
b1010100 1
b1010100 A
1'
#220000
0'
#225000
b1011100 2
b1011100 ?
b1011000 @
b1011000 1
b1011000 A
1'
#230000
0'
#235000
b1100000 2
b1100000 ?
b1011100 @
b1011100 1
b1011100 A
1'
#240000
0'
#245000
b1100100 2
b1100100 ?
b1100000 @
b1100000 1
b1100000 A
1'
#250000
0'
#255000
b1101000 2
b1101000 ?
b1100100 @
b1100100 1
b1100100 A
1'
#260000
0'
#265000
b1101100 2
b1101100 ?
b1101000 @
b1101000 1
b1101000 A
1'
#270000
0'
#275000
b1110000 2
b1110000 ?
b1101100 @
b1101100 1
b1101100 A
1'
#280000
0'
#285000
b1110100 2
b1110100 ?
b1110000 @
b1110000 1
b1110000 A
1'
#290000
0'
#295000
b1111000 2
b1111000 ?
b1110100 @
b1110100 1
b1110100 A
1'
#300000
0'
#305000
b1111100 2
b1111100 ?
b1111000 @
b1111000 1
b1111000 A
1'
#310000
0'
#315000
b10000000 2
b10000000 ?
b1111100 @
b1111100 1
b1111100 A
1'
#320000
0'
#325000
b10000100 2
b10000100 ?
b10000000 @
b10000000 1
b10000000 A
1'
#330000
0'
#335000
b10001000 2
b10001000 ?
b10000100 @
b10000100 1
b10000100 A
1'
#340000
0'
#345000
b10001100 2
b10001100 ?
b10001000 @
b10001000 1
b10001000 A
1'
#350000
0'
#355000
b10010000 2
b10010000 ?
b10001100 @
b10001100 1
b10001100 A
1'
#360000
0'
#365000
b10010100 2
b10010100 ?
b10010000 @
b10010000 1
b10010000 A
1'
#370000
0'
#375000
b10011000 2
b10011000 ?
b10010100 @
b10010100 1
b10010100 A
1'
#380000
0'
#385000
b10011100 2
b10011100 ?
b10011000 @
b10011000 1
b10011000 A
1'
#390000
0'
#395000
b10100000 2
b10100000 ?
b10011100 @
b10011100 1
b10011100 A
1'
#400000
0'
#405000
b10100100 2
b10100100 ?
b10100000 @
b10100000 1
b10100000 A
1'
#410000
0'
#415000
b10101000 2
b10101000 ?
b10100100 @
b10100100 1
b10100100 A
1'
#420000
0'
#425000
b10101100 2
b10101100 ?
b10101000 @
b10101000 1
b10101000 A
1'
#430000
0'
#435000
b10110000 2
b10110000 ?
b10101100 @
b10101100 1
b10101100 A
1'
#440000
0'
#445000
b10110100 2
b10110100 ?
b10110000 @
b10110000 1
b10110000 A
1'
#450000
0'
#455000
b10111000 2
b10111000 ?
b10110100 @
b10110100 1
b10110100 A
1'
#460000
0'
#465000
b10111100 2
b10111100 ?
b10111000 @
b10111000 1
b10111000 A
1'
#470000
0'
#475000
b11000000 2
b11000000 ?
b10111100 @
b10111100 1
b10111100 A
1'
#480000
0'
#485000
b11000100 2
b11000100 ?
b11000000 @
b11000000 1
b11000000 A
1'
#490000
0'
#495000
b11001000 2
b11001000 ?
b11000100 @
b11000100 1
b11000100 A
1'
#500000
0'
#505000
b11001100 2
b11001100 ?
b11001000 @
b11001000 1
b11001000 A
1'
